snapbox.py
snapbox-0.1.2.dist-info/LICENSE
snapbox-0.1.2.dist-info/METADATA
snapbox-0.1.2.dist-info/WHEEL
snapbox-0.1.2.dist-info/entry_points.txt
snapbox-0.1.2.dist-info/top_level.txt
snapbox-0.1.2.dist-info/RECORD
