Metadata-Version: 2.1
Name: snapbox
Version: 0.1.2
Summary: Draw boxes over images.
Author-email: Artur Barseghyan <artur.barseghyan@gmail.com>
License: MIT
Project-URL: Homepage, https://github.com/barseghyanartur/snapbox/
Project-URL: Bug Tracker, https://github.com/barseghyanartur/snapbox/issues
Project-URL: Documentation, https://snapbox.readthedocs.io/
Project-URL: Source Code, https://github.com/barseghyanartur/snapbox/
Project-URL: Changelog, https://snapbox.readthedocs.io/en/latest/changelog.html
Keywords: box,image
Classifier: Development Status :: 4 - Beta
Classifier: Intended Audience :: Developers
Classifier: License :: OSI Approved :: MIT License
Classifier: Operating System :: OS Independent
Classifier: Programming Language :: Python :: 3
Classifier: Programming Language :: Python :: 3.10
Classifier: Programming Language :: Python :: 3.11
Classifier: Programming Language :: Python :: 3.12
Classifier: Programming Language :: Python :: 3.7
Classifier: Programming Language :: Python :: 3.8
Classifier: Programming Language :: Python :: 3.9
Classifier: Programming Language :: Python
Classifier: Topic :: Software Development :: Testing
Classifier: Topic :: Software Development
License-File: LICENSE
Requires-Dist: Pillow
Provides-Extra: all
Requires-Dist: snapbox[dev,docs,test] ; extra == 'all'
Provides-Extra: dev
Requires-Dist: black ; extra == 'dev'
Requires-Dist: detect-secrets ; extra == 'dev'
Requires-Dist: doc8 ; extra == 'dev'
Requires-Dist: ipython ; extra == 'dev'
Requires-Dist: isort ; extra == 'dev'
Requires-Dist: mypy ; extra == 'dev'
Requires-Dist: pip-tools ; extra == 'dev'
Requires-Dist: pydoclint ; extra == 'dev'
Requires-Dist: ruff ; extra == 'dev'
Requires-Dist: twine ; extra == 'dev'
Requires-Dist: uv ; extra == 'dev'
Provides-Extra: docs
Requires-Dist: sphinx <6.0 ; extra == 'docs'
Requires-Dist: sphinx-rtd-theme >=1.3.0 ; extra == 'docs'
Requires-Dist: sphinx-no-pragma ; extra == 'docs'
Provides-Extra: test
Requires-Dist: pytest ; extra == 'test'
Requires-Dist: pytest-cov ; extra == 'test'
Requires-Dist: pytest-rst ; extra == 'test'
